sigfoxapi/__init__.py
sigfoxapi/requesthandler.py
sigfoxapi-0.3.0.dist-info/DESCRIPTION.rst
sigfoxapi-0.3.0.dist-info/METADATA
sigfoxapi-0.3.0.dist-info/RECORD
sigfoxapi-0.3.0.dist-info/WHEEL
sigfoxapi-0.3.0.dist-info/metadata.json
sigfoxapi-0.3.0.dist-info/top_level.txt
