Metadata-Version: 2.0
Name: sigfoxapi
Version: 0.3.0
Summary: Python wrapper for the Sigfox backend REST API
Home-page: https://github.com/mjuenema/python-sigfox-backend-api
Author: Markus Juenemann
Author-email: markus@juenemann.net
License: BSD 2-clause "Simplified" License
Keywords: sigfox
Platform: UNKNOWN
Classifier: Development Status :: 4 - Beta
Classifier: Intended Audience :: Developers
Classifier: License :: OSI Approved :: BSD License
Classifier: Programming Language :: Python :: 3
Requires-Dist: drest (==0.9.12)
